My_pakage/__init__.py
My_pakage/module_1.py
reverse_text_byyashsharma-0.1.0.dist-info/licenses/LICENSE
reverse_text_byyashsharma-0.1.0.dist-info/METADATA
reverse_text_byyashsharma-0.1.0.dist-info/WHEEL
reverse_text_byyashsharma-0.1.0.dist-info/top_level.txt
reverse_text_byyashsharma-0.1.0.dist-info/RECORD
