Metadata-Version: 2.4
Name: reverse_text_byyashsharma
Version: 0.1.0
Summary: A pakage which can reverse text
Home-page: https://github.com/yash-sharma3/reverse_text_byyashsharma
Author: Yash Sharma
Author-email: Yash Sharma <yash.innovater@gmail.com>
License: MIT License
Requires-Python: >=3.6
License-File: LICENSE
Dynamic: author
Dynamic: home-page
Dynamic: license-file
Dynamic: requires-python
